event_actions/__init__.py
event_actions/constants.py
event_actions/decorators.py
event_actions/exceptions.py
event_actions/mixins.py
event_actions/models.py
django_model_event_actions-1.0.4.dist-info/LICENSE
django_model_event_actions-1.0.4.dist-info/METADATA
django_model_event_actions-1.0.4.dist-info/WHEEL
django_model_event_actions-1.0.4.dist-info/top_level.txt
django_model_event_actions-1.0.4.dist-info/RECORD
