Metadata-Version: 2.1
Name: django-model-event-actions
Version: 1.0.4
Summary: A replacement for Django Signals for a cleaner design
Home-page: https://github.com/aryabartar/django-model-event-actions
Author: Arya Khaligh
Author-email: bartararya@gmail.com
License: MIT
Keywords: django model signals event handler
Platform: any
Classifier: Development Status :: 3 - Alpha
Classifier: Intended Audience :: Developers
Classifier: License :: OSI Approved :: MIT License
Classifier: Operating System :: OS Independent
Classifier: Programming Language :: Python
Classifier: Programming Language :: Python :: 3.6
Classifier: Programming Language :: Python :: 3.7
Classifier: Programming Language :: Python :: 3.8
Classifier: Topic :: Software Development :: Libraries :: Python Modules
Requires-Python: >=3.6
License-File: LICENSE
